{"help": "https://ckan.publishing.service.gov.uk/api/3/action/help_show?name=package_show", "success": true, "result": {"contact-email": "data.manager@cefas.co.uk", "creator_user_id": "60e687bf-a6d8-43e2-a50e-efab84b27952", "id": "3726b4f5-df7a-402c-83f8-2302a3137e03", "isopen": true, "license_id": "uk-ogl", "license_title": "UK Open Government Licence (OGL)", "license_url": "http://reference.data.gov.uk/id/open-government-licence", "metadata_created": "2015-07-06T14:02:15.388150", "metadata_modified": "2020-09-16T06:22:25.854176", "name": "1976-1976-centre-for-environment-fisheries-aquaculture-science-cefas-west-central-north-s-13-76", "notes": "<span style=\"font-family: 'Trebuchet MS','sans-serif'; color: \nblack;\">...</span>\n\n\n\n", "num_resources": 1, "num_tags": 0, "organization": {"id": "2f1c6ccb-3f21-40c0-8b26-41566c53eb2f", "name": "centre-for-environment-fisheries-aquaculture-science", "title": "Centre for Environment, Fisheries & Aquaculture Science", "type": "organization", "description": "The Centre for Environment, Fisheries and Aquaculture Science (Cefas) is a world leader in marine science and technology, providing innovative solutions for the aquatic environment, biodiversity and food security.\r\n", "image_url": "", "created": "2012-06-27T14:50:51.521004", "is_organization": true, "approval_status": "pending", "state": "active"}, "owner_org": "2f1c6ccb-3f21-40c0-8b26-41566c53eb2f", "private": false, "state": "active", "temporal_coverage-from": ["1976-09-28"], "temporal_coverage-to": ["1976-10-13"], "title": "1976 - 1976 Centre for Environment, Fisheries & Aquaculture Science (Cefas) West Central North Sea Plankton Survey - RV Corella 13/76", "type": "dataset", "url": null, "version": null, "extras": [{"key": "UKLP", "value": "True"}, {"key": "access_constraints", "value": "[\"Public data (Crown Copyright) - Open Government Licence Terms and Conditions apply\"]"}, {"key": "bbox-east-long", "value": "4"}, {"key": "bbox-north-lat", "value": "56.5"}, {"key": "bbox-south-lat", "value": "52.5"}, {"key": "bbox-west-long", "value": "-2"}, {"key": "coupled-resource", "value": "[]"}, {"key": "dataset-reference-date", "value": "[{\"type\": \"publication\", \"value\": \"2019-10-24\"}]"}, {"key": "frequency-of-update", "value": "notPlanned"}, {"key": "guid", "value": "CEFAS1a27b77a-d13d-4ff1-b0c0-eef650cc5531"}, {"key": "licence", "value": "[\"Public data (Crown Copyright) - Open Government Licence Terms and Conditions apply\"]"}, {"key": "metadata-date", "value": "2019-10-24T09:24:44"}, {"key": "metadata-language", "value": "eng"}, {"key": "progress", "value": ""}, {"key": "provider", "value": ""}, {"key": "resource-type", "value": "dataset"}, {"key": "responsible-party", "value": "Centre for Environment, Fisheries & Aquaculture Science (originator, custodian)"}, {"key": "spatial", "value": "{\"type\": \"Polygon\", \"coordinates\": [[[4, 52.5], [-2, 52.5], [-2, 56.5], [4, 56.5], [4, 52.5]]]}"}, {"key": "spatial-data-service-type", "value": ""}, {"key": "spatial-reference-system", "value": "urn:ogc:def:crs:EPSG::4326"}], "resources": [{"cache_last_updated": null, "cache_url": null, "created": "2020-09-16T06:22:26.096695", "description": "Resource locator", "format": "", "hash": "", "id": "7c3a1b5b-46ac-4209-96fd-1489fb6a72fe", "last_modified": null, "metadata_modified": "2020-09-16T06:22:26.096695", "mimetype": null, "mimetype_inner": null, "name": "", "package_id": "3726b4f5-df7a-402c-83f8-2302a3137e03", "position": 0, "resource_locator_function": "order", "resource_locator_protocol": "", "resource_type": null, "size": null, "state": "active", "url": "http://data.cefas.co.uk/#/View/2526/", "url_type": null}], "tags": [], "groups": [], "relationships_as_subject": [], "relationships_as_object": [], "harvest": [{"key": "harvest_object_id", "value": "2002bca3-7e75-4c75-9e07-b69e1d683093"}, {"key": "harvest_source_id", "value": "1a2a2e3d-a51e-4046-8c8b-e8ad3856dd9d"}, {"key": "harvest_source_title", "value": "Cefas WAF endpoint for data.gov.uk"}]}}