{"help": "https://ckan.publishing.service.gov.uk/api/3/action/help_show?name=package_show", "success": true, "result": {"owner_org": "c756c8da-f176-4640-950e-9c00b9e404df", "temporal_coverage-from": ["2005-01-01"], "relationships_as_object": [], "private": false, "num_tags": 0, "id": "9fd42b7c-a495-4692-9fa4-895adcae4a5e", "metadata_created": "2019-08-29T05:49:28.767326", "metadata_modified": "2019-08-29T05:49:28.767331", "state": "active", "version": null, "temporal_coverage-to": ["2006-12-31"], "license_id": null, "type": "dataset", "resources": [], "num_resources": 0, "contact-email": "kdawson@dorsetwildlifetrust.org.uk", "tags": [], "title": "2005 - 2006 Purbeck Marine Wildlife Reserve, Kimmeridge Dorset, Marine Wildlife Recordings and Sightings", "groups": [], "creator_user_id": "fe27eda4-4fcf-46e5-8818-5fdb2b0a52f9", "relationships_as_subject": [], "name": "2005-2006-purbeck-marine-wildlife-reserve-kimmeridge-dorset-marine-wildlife-recordings-and-sigh1", "isopen": false, "url": null, "notes": "Sightings and recordings made by staff of and visitors to the Purbeck Marine Wildlife Reserve. Details taken from the marine recording logs from the reserve centre. Where divers and walkers have made sightings recorder is entered as 'PMWR visitor'. Not all records are from the area defined as the PMWR, but have been logged at the centre by visitors.", "license_title": null, "extras": [{"value": "True", "key": "UKLP"}, {"value": "[\"No restrictions to public access\"]", "key": "access_constraints"}, {"value": "-1.6915", "key": "bbox-east-long"}, {"value": "50.7357", "key": "bbox-north-lat"}, {"value": "50.3396", "key": "bbox-south-lat"}, {"value": "-2.9460", "key": "bbox-west-long"}, {"value": "[]", "key": "coupled-resource"}, {"value": "[{\"type\": \"publication\", \"value\": \"2013-02-11\"}]", "key": "dataset-reference-date"}, {"value": "notPlanned", "key": "frequency-of-update"}, {"value": "8f118584-decc-442b-8e7d-3f1d0a6aa261", "key": "guid"}, {"value": "[\"Data is freely available for research or commercial use providing that the originators are acknowledged in any publications produced.\"]", "key": "licence"}, {"value": "2016-11-15", "key": "metadata-date"}, {"value": "eng", "key": "metadata-language"}, {"value": "", "key": "progress"}, {"value": "", "key": "provider"}, {"value": "dataset", "key": "resource-type"}, {"value": "No organisation (originator); Dorset Wildlife Trust (originator, custodian); Dorset Environmental Record Centre (custodian)", "key": "responsible-party"}, {"value": "{\"type\": \"Polygon\", \"coordinates\": [[[-1.6915, 50.3396], [-2.9460, 50.3396], [-2.9460, 50.7357], [-1.6915, 50.7357], [-1.6915, 50.3396]]]}", "key": "spatial"}, {"value": "", "key": "spatial-data-service-type"}, {"value": "urn:ogc:def:crs:EPSG::4326", "key": "spatial-reference-system"}], "organization": {"description": "MEDIN is a partnership of UK organisations committed to improving access to marine data. Our partners are both public and private sector.", "title": "Marine Environmental Data & Information Network", "created": "2012-06-27T14:54:56.935179", "approval_status": "pending", "is_organization": true, "state": "active", "image_url": "", "revision_id": "601023a8-028c-4a57-afc8-6e37cb2333e5", "type": "organization", "id": "c756c8da-f176-4640-950e-9c00b9e404df", "name": "marine-environmental-data-information-network"}, "revision_id": "6bb5aba8-dd14-477c-a19d-9280cddf9595", "harvest": [{"key": "harvest_object_id", "value": "a4b59a4c-2f8c-4434-a1a8-f330e5ae40d5"}, {"key": "harvest_source_id", "value": "885ee504-c712-4f8d-9034-1c230bcd88a6"}, {"key": "harvest_source_title", "value": "Marine Environmental Data Information Network (MEDIN) node hosted by MARIS (Netherlands)"}]}}