{"help": "https://ckan.publishing.service.gov.uk/api/3/action/help_show?name=package_show", "success": true, "result": {"owner_org": "17e00404-a853-49ca-9ea2-6db8cceaf1e2", "groups": [], "temporal_coverage-from": "2010-05-17", "relationships_as_object": [], "unpublished": false, "private": false, "num_tags": 0, "foi-email": "", "update_frequency": "", "odi-certificate": {"status": "final", "jurisdiction": "GB", "title": "2011 skills for life survey small area estimation datasets", "created_at": "2014-10-29T19:20:52Z", "level": "bronze", "certificate_url": "https://certificates.theodi.org/en/datasets/13411/certificate", "source": "Automatically awarded by ODI", "certification_type": "automatically awarded", "badge_url": "https://certificates.theodi.org/en/datasets/13411/certificate/badge.png", "cert_title": "Bronze level certificate"}, "id": "bb8aafb1-a6c5-400a-9bc3-41ccb119bef2", "metadata_created": "2012-12-13T18:26:40.646363", "metadata_modified": "2017-02-09T19:29:21.447012", "state": "active", "version": null, "core-dataset": false, "temporal_coverage-to": "2011-02-25", "license_id": "uk-ogl", "foi-web": "", "resources": [{"cache_last_updated": null, "cache_url": null, "mimetype_inner": null, "description": "2011 skills for life survey main reports", "format": "PDF", "url": "https://www.gov.uk/government/publications/2011-skills-for-life-survey", "created": "2012-12-13T18:26:40.842820", "state": "active", "package_id": "bb8aafb1-a6c5-400a-9bc3-41ccb119bef2", "last_modified": null, "mimetype": null, "url_type": null, "position": 0, "revision_id": "6773cab6-21b8-47c5-a02c-d5c71f23a151", "size": null, "id": "86d7a903-94f7-4d7d-9c5b-06601cf9ab76", "resource_type": "documentation", "name": null}, {"cache_last_updated": null, "cache_url": null, "mimetype_inner": null, "description": "2011 skills for life survey: headline findings", "format": "PDF", "url": "https://www.gov.uk/government/publications/skills-for-life-survey-2011-important-findings", "created": "2012-12-13T18:26:40.842844", "state": "active", "package_id": "bb8aafb1-a6c5-400a-9bc3-41ccb119bef2", "last_modified": null, "mimetype": null, "url_type": null, "position": 1, "revision_id": "6773cab6-21b8-47c5-a02c-d5c71f23a151", "size": null, "id": "0d1a7433-6eb7-4cde-93b0-e303e18f3709", "resource_type": "documentation", "name": null}, {"cache_last_updated": null, "cache_url": null, "mimetype_inner": null, "description": "2011 skills for life survey small area estimation datasets", "format": "CSV", "url": "https://www.gov.uk/government/statistical-data-sets/2011-skills-for-life-survey-small-area-estimation-data", "created": "2012-12-13T18:26:40.842854", "state": "active", "package_id": "bb8aafb1-a6c5-400a-9bc3-41ccb119bef2", "last_modified": null, "mimetype": null, "url_type": null, "position": 2, "revision_id": "6773cab6-21b8-47c5-a02c-d5c71f23a151", "size": null, "id": "bc9c2262-37af-439f-9960-2a3347cf46f9", "resource_type": "file", "name": null}], "num_resources": 3, "contact-email": "", "tags": [], "title": "2011 skills for life survey small area estimation datasets", "foi-name": "", "contact-phone": "", "creator_user_id": "22d08eaf-90d6-47c5-88a6-b4023fd703e5", "relationships_as_subject": [], "geographic_coverage": "100000: England", "contact-name": "", "name": "2011-skills-for-life-survey-anonymised-dataset", "isopen": true, "url": null, "type": "dataset", "notes": "These data are modelled estimates of literacy , numeracy and ICT skills in lower-level geographies in England. Small Area Estimation modelling methods have been applied to the 2011 Skills for Life survey data in order to generate local level area estimates of: the number and proportion of adults (aged 16-64 years old) in England living in households with defined skill levels in: literacy, numeracy and ICT, including emailing, word processing, spreadsheet use and a multiple-choice assessment of ICT awareness. The number and proportion of adults in households who do not speak English as a first language are also included. Two sets of Small Area Estimates are provided for seven geographies: Middle Layer Super Output Areas (MSOAs), Standard Table Wards, 2005 Statistical Wards, 2011 Council Wards, 2011 Parliamentary Constituencies, Local Authorities, and Local Enterprise Partnership areas. Regional estimates have also been provided, however, unlike the other geographies, these estimates are based on direct survey.", "license_title": "UK Open Government Licence (OGL)", "theme-secondary": ["Society"], "extras": [{"value": "false", "key": "its-dataset"}, {"value": "2012-12-14T09:08:51.173164", "key": "last_major_modification"}, {"value": "false", "key": "register"}, {"value": "", "key": "sla"}], "license_url": "http://reference.data.gov.uk/id/open-government-licence", "organization": {"description": "The Department for Education is responsible for education and children\u2019s services in England. We work to achieve a highly educated society in which opportunity is equal for children and young people, no matter what their background or family circumstances.\r\nDfE is a ministerial department, supported by 9 agencies and public bodies.\r\n\r\nhttps://www.gov.uk/government/organisations/department-for-education", "title": "Department for Education", "created": "2012-06-27T14:48:37.708077", "approval_status": "pending", "is_organization": true, "state": "active", "image_url": "", "revision_id": "6b86a492-0012-4389-80ea-f1b374e02ac4", "type": "organization", "id": "17e00404-a853-49ca-9ea2-6db8cceaf1e2", "name": "department-for-education"}, "revision_id": "b71cc6ef-4cd2-49e8-a5c8-deca93437649", "foi-phone": "", "theme-primary": "education"}}