{"help": "https://ckan.publishing.service.gov.uk/api/3/action/help_show?name=package_show", "success": true, "result": {"owner_org": "b1472b4f-b8c8-4ac2-9701-76995445f99b", "temporal_coverage-from": [], "relationships_as_object": [], "private": false, "num_tags": 0, "id": "a91bce60-9eb2-4e66-a11a-190938d2c422", "metadata_created": "2015-12-17T12:05:02.681656", "metadata_modified": "2016-02-10T17:04:16.293097", "state": "active", "version": null, "temporal_coverage-to": [], "license_id": "uk-ogl", "type": "dataset", "resources": [{"cache_last_updated": null, "package_id": "a91bce60-9eb2-4e66-a11a-190938d2c422", "id": "4ce1322d-5611-4756-8c42-76ace5f5b032", "size": null, "state": "active", "resource_locator_function": "download", "archiver": "{'is_broken_printable': 'Downloaded OK', 'updated': '2016-02-05T22:01:33.867864', 'cache_filepath': u'/media/hulk/ckan_resource_cache/4c/4ce1322d-5611-4756-8c42-76ace5f5b032/download', 'last_success': '2016-02-05T22:01:33.867864', 'size': u'29031', 'is_broken': False, 'failure_count': 0, 'etag': None, 'status': 'Archived successfully', 'url_redirected_to': None, 'hash': u'66e3308a1f8437f8f624d947c0f00fa2aecc8aaa', 'status_id': 0, 'reason': u'', 'last_modified': None, 'resource_timestamp': '2015-12-17T15:33:03.451565', 'mimetype': u'text/html', 'cache_url': u'http://data.gov.uk/data/resource_cache/4c/4ce1322d-5611-4756-8c42-76ace5f5b032/download', 'created': '2015-12-17T13:15:49.765743', 'first_failure': None}", "hash": "", "description": "download", "format": "HTML", "mimetype_inner": null, "url_type": null, "resource_locator_protocol": "", "mimetype": null, "cache_url": null, "name": "Download from the \u201cEUNIS habitat maps from surveys\u201d package, Broad, Medium and Fine scale data", "created": "2015-12-17T12:05:02.764070", "url": "http://www.emodnet-seabedhabitats.eu/download", "qa": "{'updated': '2016-02-05T22:03:19.298649', 'openness_score': 0, 'archival_timestamp': '2016-02-05T22:01:33.867864', 'format': u'HTML', 'created': '2015-12-17T15:33:03.428227', 'resource_timestamp': None, 'openness_score_reason': u'Content of file appeared to be format \"HTML\" which receives openness score: 0.'}", "last_modified": null, "position": 0, "revision_id": "e04b3abb-5b4a-437d-aadf-55453bba6470", "resource_type": "file"}, {"cache_last_updated": null, "package_id": "a91bce60-9eb2-4e66-a11a-190938d2c422", "id": "32ca88b1-4de3-4109-9f2f-0deba241fb3e", "size": null, "state": "active", "resource_locator_function": "information", "archiver": "{'is_broken_printable': 'Downloaded OK', 'updated': '2016-02-05T22:01:34.887203', 'cache_filepath': u'/media/hulk/ckan_resource_cache/32/32ca88b1-4de3-4109-9f2f-0deba241fb3e/map', 'last_success': '2016-02-05T22:01:34.887203', 'size': u'273278', 'is_broken': False, 'failure_count': 0, 'etag': None, 'status': 'Archived successfully', 'url_redirected_to': None, 'hash': u'0462588854c41ab3585300ea1f87e392b984c772', 'status_id': 0, 'reason': u'', 'last_modified': None, 'resource_timestamp': '2015-12-17T15:33:03.451565', 'mimetype': u'text/html', 'cache_url': u'http://data.gov.uk/data/resource_cache/32/32ca88b1-4de3-4109-9f2f-0deba241fb3e/map', 'created': '2015-12-17T13:15:50.751655', 'first_failure': None}", "hash": "", "description": "information", "format": "HTML", "mimetype_inner": null, "url_type": null, "resource_locator_protocol": "", "mimetype": null, "cache_url": null, "name": "Interactive map", "created": "2015-12-17T12:05:02.764089", "url": "http://www.emodnet-seabedhabitats.eu/map", "qa": "{'updated': '2016-02-05T22:03:19.309576', 'openness_score': 0, 'archival_timestamp': '2016-02-05T22:01:34.887203', 'format': u'HTML', 'created': '2015-12-17T15:33:03.440924', 'resource_timestamp': None, 'openness_score_reason': u'Content of file appeared to be format \"HTML\" which receives openness score: 0.'}", "last_modified": null, "position": 1, "revision_id": "e04b3abb-5b4a-437d-aadf-55453bba6470", "resource_type": "file"}, {"verified_date": "2015-12-17T12:05:01.512071", "cache_last_updated": null, "package_id": "a91bce60-9eb2-4e66-a11a-190938d2c422", "id": "a3262093-063a-4c11-8aaa-8e2701441314", "size": null, "verified": "True", "state": "active", "resource_locator_function": "information", "archiver": "{'is_broken_printable': 'Downloaded OK', 'updated': '2016-02-05T22:01:35.430806', 'cache_filepath': u'/media/hulk/ckan_resource_cache/a3/a3262093-063a-4c11-8aaa-8e2701441314/mapserv.exe', 'last_success': '2016-02-05T22:01:35.430806', 'size': u'1104', 'is_broken': False, 'failure_count': 0, 'etag': None, 'status': 'Archived successfully', 'url_redirected_to': u'http://213.122.160.75/scripts/mapserv.exe?map=D:%5CWebsites%5CMESHAtlantic%5Cmap%5CMESHAtlanticWMS.map', 'hash': u'ffa365d8ce539175ccff2f00020ae7a1d56faaa7', 'status_id': 0, 'reason': u'', 'last_modified': None, 'resource_timestamp': '2015-12-17T12:05:02.681656', 'mimetype': u'text/html', 'cache_url': u'http://data.gov.uk/data/resource_cache/a3/a3262093-063a-4c11-8aaa-8e2701441314/mapserv.exe', 'created': '2015-12-17T13:15:51.395680', 'first_failure': None}", "hash": "", "description": "information", "format": "WMS", "mimetype_inner": null, "url_type": null, "resource_locator_protocol": "", "mimetype": null, "cache_url": null, "name": "EMODnet Seabed Habitats WMS", "created": "2015-12-17T12:05:02.764095", "url": "http://213.122.160.75/scripts/mapserv.exe?map=D:\\Websites\\MESHAtlantic\\map\\MESHAtlanticWMS.map", "wms_base_urls": "http://213.122.160.75/scripts/mapserv.exe", "qa": "{'updated': '2016-02-05T22:03:19.318013', 'openness_score': 0, 'archival_timestamp': '2016-02-05T22:01:35.430806', 'format': u'HTML', 'created': '2015-12-17T15:33:03.449288', 'resource_timestamp': None, 'openness_score_reason': u'Content of file appeared to be format \"HTML\" which receives openness score: 0.'}", "last_modified": null, "ckan_recommended_wms_preview": "True", "position": 2, "revision_id": "e04b3abb-5b4a-437d-aadf-55453bba6470", "resource_type": "file"}], "num_resources": 3, "contact-email": "enquiries@naturalengland.org.uk", "tags": [], "title": "2012 DEFRA Verification Survey of Folkestone Pomerania", "groups": [], "creator_user_id": "60e687bf-a6d8-43e2-a50e-efab84b27952", "relationships_as_subject": [], "name": "2012-defra-verification-survey-of-folkestone-pomerania", "isopen": true, "url": null, "notes": "Folkestone Pomerania rMCZ verification survey conducted by CEFAS on behalf of DEFRA. The purpose of the study was to produce an updated Habitat map to inform on the presence of Broad Scale Habitats, Habitat FOCI and estimate spatial extent within the rMCZ, as well as providing evidence of the presence of Species FOCI. The study comprised of acoustic data acquisition and interpretation followed by groundtruthing. Groundtruthing was conducted using a Hamon Grab and Underwater Video and Stills camera.", "license_title": "UK Open Government Licence (OGL)", "theme-secondary": [], "extras": [{"value": "True", "key": "UKLP"}, {"value": "[\"Publicly accessible: NE-OS OGL\"]", "key": "access_constraints"}, {"value": "1.34163", "key": "bbox-east-long"}, {"value": "51.05563", "key": "bbox-north-lat"}, {"value": "50.98879", "key": "bbox-south-lat"}, {"value": "1.218209218", "key": "bbox-west-long"}, {"value": "[]", "key": "coupled-resource"}, {"value": "[{\"type\": \"publication\", \"value\": \"2004-01-01\"}]", "key": "dataset-reference-date"}, {"value": "asNeeded", "key": "frequency-of-update"}, {"value": "f07df1fc-7ef3-4dc8-9f83-c964a53e158b", "key": "guid"}, {"value": "https://locationmde.data.gov.uk/metadata-harvesting/b1472b4f-b8c8-4ac2-9701-76995445f99b/348-GB100213.xml", "key": "harvest_source_reference"}, {"value": "harvest", "key": "import_source"}, {"value": "No conditions apply. By using this data you are accepting the terms of the Natural England-OS Open Government Licence (https://www.gov.uk/how-to-access-natural-englands-maps-and-data#terms-and-conditions-for-use-of-data). For further info contact Natural England 0300 060 3900 enquiries@naturalengland.org.uk", "key": "licence"}, {"value": "2015-12-17", "key": "metadata-date"}, {"value": "eng", "key": "metadata-language"}, {"value": "", "key": "provider"}, {"value": "dataset", "key": "resource-type"}, {"value": "Natural England (custodian)", "key": "responsible-party"}, {"value": "{\"type\":\"Polygon\",\"coordinates\":[[[1.34163, 50.98879],[1.34163, 51.05563], [1.218209218, 51.05563], [1.218209218, 50.98879], [1.34163, 50.98879]]]}", "key": "spatial"}, {"value": "", "key": "spatial-data-service-type"}, {"value": "WGS 1984", "key": "spatial-reference-system"}], "license_url": "http://reference.data.gov.uk/id/open-government-licence", "organization": {"description": "", "title": "Natural England", "created": "2012-06-27T14:50:10.959130", "approval_status": "pending", "is_organization": true, "state": "active", "image_url": "", "revision_id": "22dd4e62-a3b9-4ffe-9021-adbfbfb41ffb", "type": "organization", "id": "b1472b4f-b8c8-4ac2-9701-76995445f99b", "name": "natural-england"}, "revision_id": "e04b3abb-5b4a-437d-aadf-55453bba6470", "theme-primary": "environment", "harvest": [{"key": "harvest_object_id", "value": "92d6f5b8-012c-41d2-8654-e15b59571fc3"}, {"key": "harvest_source_id", "value": "0b3f58b3-bed5-41eb-b105-b4d1b4d6ab75"}, {"key": "harvest_source_title", "value": "Natural England UKME WAF"}]}}