{"help": "https://ckan.publishing.service.gov.uk/api/3/action/help_show?name=package_show", "success": true, "result": {"contact-email": "jase@mba.ac.uk", "creator_user_id": "fe27eda4-4fcf-46e5-8818-5fdb2b0a52f9", "id": "457b828a-9bb1-48c2-a9d5-1f62ab5c6388", "isopen": false, "license_id": null, "license_title": null, "metadata_created": "2023-02-01T19:07:42.108954", "metadata_modified": "2023-02-01T19:07:42.108958", "name": "2016-marine-biological-association-of-the-uk-mba-mothecombe-seine-net-and-push-net-fish-survey6", "notes": "A site at Mothecombe was surveyed using two different methods. Push netting and seine netting were carried out at Meadowsfoot Beach near Owen's Point. The species caught, by both methods, were recorded to species level where possible. Both the frequency (count data) and the lengths of each individual were captured.", "num_resources": 2, "num_tags": 0, "organization": {"id": "c756c8da-f176-4640-950e-9c00b9e404df", "name": "marine-environmental-data-information-network", "title": "Marine Environmental Data & Information Network", "type": "organization", "description": "MEDIN is a partnership of UK organisations committed to improving access to marine data. Our partners are both public and private sector.", "image_url": "", "created": "2012-06-27T14:54:56.935179", "is_organization": true, "approval_status": "pending", "state": "active"}, "owner_org": "c756c8da-f176-4640-950e-9c00b9e404df", "private": false, "state": "active", "temporal_coverage-from": ["2016-07-05"], "temporal_coverage-to": ["2017-11-09"], "title": "2016 Marine Biological Association of the UK (MBA) Mothecombe Seine Net and Push Net Fish Survey", "type": "dataset", "url": null, "version": null, "extras": [{"key": "UKLP", "value": "True"}, {"key": "access_constraints", "value": "[\"DASSH Terms and Conditions apply (http://www.dassh.ac.uk/terms-and-conditions)\"]"}, {"key": "bbox-east-long", "value": "-3.9427"}, {"key": "bbox-north-lat", "value": "50.3152"}, {"key": "bbox-south-lat", "value": "50.3062"}, {"key": "bbox-west-long", "value": "-3.9561"}, {"key": "coupled-resource", "value": "[]"}, {"key": "dataset-reference-date", "value": "[{\"type\": \"publication\", \"value\": \"2016-08-23\"}]"}, {"key": "frequency-of-update", "value": "notPlanned"}, {"key": "guid", "value": "99a1bb6a-1ed4-47ec-b966-59b83078e63b"}, {"key": "licence", "value": "[\"DASSH Terms and Conditions apply (http://www.dassh.ac.uk/terms-and-conditions)\"]"}, {"key": "metadata-date", "value": "2019-08-23"}, {"key": "metadata-language", "value": "eng"}, {"key": "progress", "value": ""}, {"key": "provider", "value": ""}, {"key": "resource-type", "value": "dataset"}, {"key": "responsible-party", "value": "Marine Biological Association of the UK (MBA) (originator); Data Archive for Seabed Species and Habitats (DASSH) (custodian)"}, {"key": "spatial", "value": "{\"type\": \"Polygon\", \"coordinates\": [[[-3.9427, 50.3062], [-3.9561, 50.3062], [-3.9561, 50.3152], [-3.9427, 50.3152], [-3.9427, 50.3062]]]}"}, {"key": "spatial-data-service-type", "value": ""}, {"key": "spatial-reference-system", "value": "urn:ogc:def:crs:EPSG::4326"}], "resources": [{"cache_last_updated": null, "cache_url": null, "created": "2023-02-01T19:07:42.111267", "description": "A link to the web service or dataset", "format": "", "hash": "", "id": "b379dfb9-3e9c-4d26-acb9-667bf4c37209", "last_modified": null, "metadata_modified": "2023-02-01T19:07:42.105812", "mimetype": null, "mimetype_inner": null, "name": "Click to get data", "package_id": "457b828a-9bb1-48c2-a9d5-1f62ab5c6388", "position": 0, "resource_locator_function": "", "resource_locator_protocol": "", "resource_type": null, "size": null, "state": "active", "url": "http://www.dassh.ac.uk/datasets/DASSHDT00000285", "url_type": null}, {"cache_last_updated": null, "cache_url": null, "created": "2023-02-01T19:07:42.111270", "description": "A link to the general host site", "format": "", "hash": "", "id": "1472524b-23bb-47f8-9b05-7d686fda128f", "last_modified": null, "metadata_modified": "2023-02-01T19:07:42.105964", "mimetype": null, "mimetype_inner": null, "name": "DASSH website", "package_id": "457b828a-9bb1-48c2-a9d5-1f62ab5c6388", "position": 1, "resource_locator_function": "", "resource_locator_protocol": "", "resource_type": null, "size": null, "state": "active", "url": "http://www.dassh.ac.uk", "url_type": null}], "tags": [], "groups": [], "relationships_as_subject": [], "relationships_as_object": [], "harvest": [{"key": "harvest_object_id", "value": "acc4303f-cf50-46ee-b8fc-040e547a92ef"}, {"key": "harvest_source_id", "value": "885ee504-c712-4f8d-9034-1c230bcd88a6"}, {"key": "harvest_source_title", "value": "Marine Environmental Data Information Network (MEDIN) node hosted by MARIS (Netherlands)"}]}}